langchange-0.1.0.dist-info/licenses/LICENSE
languagechange/__init__.py
languagechange/benchmark.py
languagechange/cache.py
languagechange/corpora.py
languagechange/evaluation.py
languagechange/resource_manager.py
languagechange/resources_hub.json
languagechange/search.py
languagechange/usages.py
languagechange/utils.py
languagechange/models/__init__.py
languagechange/models/change/__init__.py
languagechange/models/change/metrics.py
languagechange/models/change/timeseries.py
languagechange/models/change/widid.py
languagechange/models/meaning/__init__.py
languagechange/models/meaning/clustering.py
languagechange/models/meaning/meaning.py
languagechange/models/representation/__init__.py
languagechange/models/representation/alignment.py
languagechange/models/representation/contextualized.py
languagechange/models/representation/definition.py
languagechange/models/representation/prompting.py
languagechange/models/representation/static.py
languagechange/models/type/type_classification.py
langchange-0.1.0.dist-info/METADATA
langchange-0.1.0.dist-info/WHEEL
langchange-0.1.0.dist-info/top_level.txt
langchange-0.1.0.dist-info/RECORD
