Metadata-Version: 2.4
Name: langchange
Version: 0.1.0
Summary: Python Library for Language Change
Author: Change is Key!
License-Expression: MIT
Project-URL: Homepage, https://github.com/pierluigic/languagechange
Classifier: Programming Language :: Python :: 3
Classifier: Operating System :: OS Independent
Requires-Python: >=3.8
License-File: LICENSE
Requires-Dist: dload==0.6
Requires-Dist: LSCDetection-LanguageChange==0.0.1
Requires-Dist: WordTransformer-LanguageChange==0.0.1
Requires-Dist: datasets==4.0.0
Requires-Dist: filelock==3.12.2
Requires-Dist: gensim==4.3.3
Requires-Dist: huggingface-hub==0.25.0
Requires-Dist: jsonlines==4.0.0
Requires-Dist: langchain==0.3.27
Requires-Dist: lxml==6.0.0
Requires-Dist: numpy==1.26.4
Requires-Dist: pandas==2.3.1
Requires-Dist: peft==0.17.0
Requires-Dist: pydantic==2.11.7
Requires-Dist: scikit-learn==1.7.1
Requires-Dist: scipy==1.11.1
Requires-Dist: sentence-transformers==3.1.0
Requires-Dist: sortedcontainers==2.4.0
Requires-Dist: torch==2.0.1
Requires-Dist: transformers==4.47.1
Requires-Dist: trankit==1.1.2
Requires-Dist: tqdm==4.67.1
Requires-Dist: platformdirs==3.8.0
Provides-Extra: providers
Requires-Dist: langchain-openai==0.3.28; extra == "providers"
Requires-Dist: langchain-ibm; extra == "providers"
Requires-Dist: databricks-langchain; extra == "providers"
Dynamic: license-file
